dmarc/__init__.py
dmarc/ar.py
dmarc/asyncresolver.py
dmarc/psl.py
dmarc/resolver.py
dmarc/milter/__init__.py
dmarc/milter/__main__.py
dmarc/milter/asyncspf.py
dmarc/milter/milter.py
dmarc/milter/networkparser.py
dmarc/milter/utils.py
dmarc/report/__init__.py
dmarc/report/schemas/dmarc-relaxed.xsd
dmarc/report/schemas/dmarc.xsd
dmarc/tests/__init__.py
dmarc/tests/test_ar.py
dmarc/tests/test_asyncresolver.py
dmarc/tests/test_dmarc.py
dmarc/tests/test_psl.py
dmarc/tests/test_resolver.py
dmarc/tests/report/__init__.py
dmarc/tests/report/test_report.py
dmarc/tests/report/data/samplereport.xml
dmarc-1.1.3.dist-info/licenses/LICENSE
dmarc-1.1.3.dist-info/METADATA
dmarc-1.1.3.dist-info/WHEEL
dmarc-1.1.3.dist-info/top_level.txt
dmarc-1.1.3.dist-info/RECORD
