Metadata-Version: 2.4
Name: dmarc
Version: 1.1.3
Summary: DMARC library and milter module implemented in Python.
Home-page: https://gitlab.com/duobradovic/pydmarc
Author: Dusan Obradovic
Author-email: dusan@euracks.net
License: MIT
Keywords: dkim,spf,dmarc,email,authentication,milter,rfc7489,rfc8601
Classifier: Intended Audience :: Developers
Classifier: Programming Language :: Python :: 3
Classifier: License :: OSI Approved :: MIT License
Classifier: Operating System :: OS Independent
Classifier: Topic :: Communications :: Email :: Mail Transport Agents
Classifier: Topic :: Communications :: Email :: Filters
Classifier: Topic :: Software Development :: Libraries :: Python Modules
Requires-Python: >=3.9
License-File: LICENSE
Provides-Extra: resolver
Requires-Dist: dnspython; extra == "resolver"
Provides-Extra: ar
Requires-Dist: authres; extra == "ar"
Provides-Extra: psl
Requires-Dist: publicsuffix2; extra == "psl"
Provides-Extra: report
Requires-Dist: xmlschema; extra == "report"
Provides-Extra: milter
Requires-Dist: dnspython; extra == "milter"
Requires-Dist: authres; extra == "milter"
Requires-Dist: publicsuffix2; extra == "milter"
Requires-Dist: purepythonmilter; extra == "milter"
Requires-Dist: click; extra == "milter"
Requires-Dist: pyspf; extra == "milter"
Dynamic: author
Dynamic: author-email
Dynamic: classifier
Dynamic: description
Dynamic: description-content-type
Dynamic: home-page
Dynamic: keywords
Dynamic: license
Dynamic: license-file
Dynamic: provides-extra
Dynamic: requires-python
Dynamic: summary
